[
    {
        "count": 3,
        "datetime": "2006-01-31 00:00:00"
    },
    {
        "count": 12,
        "datetime": "2006-03-02 00:00:00"
    },
    {
        "count": 8,
        "datetime": "2006-04-01 00:00:00"
    },
    {
        "count": 3,
        "datetime": "2006-05-01 00:00:00"
    },
    {
        "count": 9,
        "datetime": "2006-05-31 00:00:00"
    },
    {
        "count": 17,
        "datetime": "2006-06-30 00:00:00"
    },
    {
        "count": 6,
        "datetime": "2006-07-30 00:00:00"
    },
    {
        "count": 13,
        "datetime": "2006-08-29 00:00:00"
    },
    {
        "count": 24,
        "datetime": "2006-09-28 00:00:00"
    },
    {
        "count": 35,
        "datetime": "2006-10-28 00:00:00"
    },
    {
        "count": 36,
        "datetime": "2006-11-27 00:00:00"
    },
    {
        "count": 53,
        "datetime": "2006-12-27 00:00:00"
    },
    {
        "count": 57,
        "datetime": "2007-01-26 00:00:00"
    },
    {
        "count": 53,
        "datetime": "2007-02-25 00:00:00"
    },
    {
        "count": 56,
        "datetime": "2007-03-27 00:00:00"
    },
    {
        "count": 71,
        "datetime": "2007-04-26 00:00:00"
    },
    {
        "count": 37,
        "datetime": "2007-05-26 00:00:00"
    },
    {
        "count": 30,
        "datetime": "2007-06-25 00:00:00"
    },
    {
        "count": 29,
        "datetime": "2007-07-25 00:00:00"
    },
    {
        "count": 49,
        "datetime": "2007-08-24 00:00:00"
    },
    {
        "count": 22,
        "datetime": "2007-09-23 00:00:00"
    },
    {
        "count": 29,
        "datetime": "2007-10-23 00:00:00"
    },
    {
        "count": 20,
        "datetime": "2007-11-22 00:00:00"
    },
    {
        "count": 11,
        "datetime": "2007-12-22 00:00:00"
    },
    {
        "count": 42,
        "datetime": "2008-01-21 00:00:00"
    },
    {
        "count": 19,
        "datetime": "2008-02-20 00:00:00"
    },
    {
        "count": 26,
        "datetime": "2008-03-21 00:00:00"
    },
    {
        "count": 26,
        "datetime": "2008-04-20 00:00:00"
    },
    {
        "count": 44,
        "datetime": "2008-05-20 00:00:00"
    },
    {
        "count": 16,
        "datetime": "2008-06-19 00:00:00"
    },
    {
        "count": 18,
        "datetime": "2008-07-19 00:00:00"
    },
    {
        "count": 46,
        "datetime": "2008-08-18 00:00:00"
    },
    {
        "count": 20,
        "datetime": "2008-09-17 00:00:00"
    },
    {
        "count": 22,
        "datetime": "2008-10-17 00:00:00"
    },
    {
        "count": 34,
        "datetime": "2008-11-16 00:00:00"
    },
    {
        "count": 35,
        "datetime": "2008-12-16 00:00:00"
    },
    {
        "count": 25,
        "datetime": "2009-01-15 00:00:00"
    }
]